MANIFEST.in
readme.md
requirements.txt
setup.py
eno/__init__.py
eno/nodes.py
eno/server.py
eno.egg-info/PKG-INFO
eno.egg-info/SOURCES.txt
eno.egg-info/dependency_links.txt
eno.egg-info/not-zip-safe
eno.egg-info/pbr.json
eno.egg-info/requires.txt
eno.egg-info/top_level.txt
scripts/run_eno_server