Metadata-Version: 1.1
Name: eno
Version: 0.0.17
Summary: eno test client
Home-page: http://github.com/endaga/eno-python
Author: Matt Ball
Author-email: matt@endaga.com
License: MIT
Download-URL: https://github.com/endaga/eno-python/tarball/0.0.17
Platform: UNKNOWN
